sourcesage/__init__.py
sourcesage/cli.py
sourcesage/core.py
sourcesage/logging_utils.py
sourcesage/config/.SourceSageignore
sourcesage/config/constants.py
sourcesage/config/language_map.json
sourcesage/modules/GitCommander.py
sourcesage/modules/__init__.py
sourcesage/modules/source_sage.py
sourcesage/modules/DiffReport/__init__.py
sourcesage/modules/DiffReport/git_diff.py
sourcesage/modules/DiffReport/markdown_report.py
sourcesage/modules/DocuSum/README.md
sourcesage/modules/DocuSum/__init__.py
sourcesage/modules/DocuSum/docusum.py
sourcesage/modules/DocuSum/file_pattern_matcher.py
sourcesage/modules/DocuSum/file_processor.py
sourcesage/modules/DocuSum/git_info_collector.py
sourcesage/modules/DocuSum/language_detector.py
sourcesage/modules/DocuSum/markdown_writer.py
sourcesage/modules/DocuSum/stats_collector.py
sourcesage/modules/DocuSum/tree_generator.py
sourcesage-7.2.2.dist-info/METADATA
sourcesage-7.2.2.dist-info/WHEEL
sourcesage-7.2.2.dist-info/entry_points.txt
sourcesage-7.2.2.dist-info/licenses/LICENSE
sourcesage-7.2.2.dist-info/RECORD
