Metadata-Version: 2.4
Name: sourcesage
Version: 7.2.2
Summary: Repository analysis tool that generates AI-friendly documentation
Project-URL: Homepage, https://github.com/Sunwood-ai-labs/SourceSage
Project-URL: Repository, https://github.com/Sunwood-ai-labs/SourceSage
Project-URL: Issues, https://github.com/Sunwood-ai-labs/SourceSage/issues
Author-email: Sunwood AI Labs <sunwood.ai.labs@gmail.com>
License: MIT
License-File: LICENSE
Keywords: ai,analysis,documentation,markdown,repository
Classifier: Development Status :: 4 - Beta
Classifier: Intended Audience :: Developers
Classifier: License :: OSI Approved :: MIT License
Classifier: Programming Language :: Python :: 3
Classifier: Programming Language :: Python :: 3.8
Classifier: Programming Language :: Python :: 3.9
Classifier: Programming Language :: Python :: 3.10
Classifier: Programming Language :: Python :: 3.11
Classifier: Programming Language :: Python :: 3.12
Classifier: Topic :: Utilities
Requires-Python: >=3.8
Requires-Dist: art
Requires-Dist: gitpython
Requires-Dist: loguru
Requires-Dist: python-dotenv
Requires-Dist: requests
Requires-Dist: rich
